{
 "aggregate_function_based_on": "",
 "color": "#CB2929",
 "creation": "2023-06-19 12:52:44.339096",
 "docstatus": 0,
 "doctype": "Number Card",
 "document_type": "Purchase Order",
 "dynamic_filters_json": "[]",
 "filters_json": "[[\"Purchase Order\",\"status\",\"=\",\"Draft\",false]]",
 "function": "Count",
 "idx": 0,
 "is_public": 1,
 "is_standard": 1,
 "label": "Purchase Order pending for Approval",
 "modified": "2023-06-26 12:33:39.776740",
 "modified_by": "Administrator",
 "module": "Advantisquartz",
 "name": "Purchase Order pending for Approval",
 "owner": "Administrator",
 "parent_document_type": "",
 "report_function": "Sum",
 "show_percentage_stats": 1,
 "stats_time_interval": "Daily",
 "type": "Document Type"
}