[
 {
  "cards": [
   {
    "card": "Material Request Pending for approval",
    "parent": "AQ Buying Dashboard",
    "parentfield": "cards",
    "parenttype": "Dashboard"
   },
   {
    "card": "Approved Material Request",
    "parent": "AQ Buying Dashboard",
    "parentfield": "cards",
    "parenttype": "Dashboard"
   },
   {
    "card": "Request for Quotation pending for approval",
    "parent": "AQ Buying Dashboard",
    "parentfield": "cards",
    "parenttype": "Dashboard"
   },
   {
    "card": "Approved Request for Quotation",
    "parent": "AQ Buying Dashboard",
    "parentfield": "cards",
    "parenttype": "Dashboard"
   },
   {
    "card": "Supplier Quotation pending for approval",
    "parent": "AQ Buying Dashboard",
    "parentfield": "cards",
    "parenttype": "Dashboard"
   },
   {
    "card": "Approved Supplier Quotation",
    "parent": "AQ Buying Dashboard",
    "parentfield": "cards",
    "parenttype": "Dashboard"
   },
   {
    "card": "Purchase Order pending for Approval",
    "parent": "AQ Buying Dashboard",
    "parentfield": "cards",
    "parenttype": "Dashboard"
   },
   {
    "card": "Approved Purchase Orders",
    "parent": "AQ Buying Dashboard",
    "parentfield": "cards",
    "parenttype": "Dashboard"
   },
   {
    "card": "Purchase Receipt pending for Approval",
    "parent": "AQ Buying Dashboard",
    "parentfield": "cards",
    "parenttype": "Dashboard"
   },
   {
    "card": "Approved Purchase Receipts",
    "parent": "AQ Buying Dashboard",
    "parentfield": "cards",
    "parenttype": "Dashboard"
   },
   {
    "card": "Completed Order",
    "parent": "AQ Buying Dashboard",
    "parentfield": "cards",
    "parenttype": "Dashboard"
   },
   {
    "card": "Partially Completed Orders",
    "parent": "AQ Buying Dashboard",
    "parentfield": "cards",
    "parenttype": "Dashboard"
   }
  ],
  "chart_options": null,
  "charts": [
   {
    "chart": "Purchase Order Trends Bar With Close Status",
    "parent": "AQ Buying Dashboard",
    "parentfield": "charts",
    "parenttype": "Dashboard",
    "width": "Full"
   },
   {
    "chart": "Material Request Analysis",
    "parent": "AQ Buying Dashboard",
    "parentfield": "charts",
    "parenttype": "Dashboard",
    "width": "Half"
   }
  ],
  "dashboard_name": "AQ Buying Dashboard",
  "docstatus": 0,
  "doctype": "Dashboard",
  "is_default": 0,
  "is_standard": 0,
  "modified": "2023-10-11 13:37:40.770509",
  "module": "Advantisquartz",
  "name": "AQ Buying Dashboard"
 },
 {
  "cards": [
   {
    "card": "Asset Repairing",
    "parent": "Gate Entry",
    "parentfield": "cards",
    "parenttype": "Dashboard"
   },
   {
    "card": "Asset Returnable",
    "parent": "Gate Entry",
    "parentfield": "cards",
    "parenttype": "Dashboard"
   },
   {
    "card": "Raw Material In",
    "parent": "Gate Entry",
    "parentfield": "cards",
    "parenttype": "Dashboard"
   },
   {
    "card": "Store & Spare In",
    "parent": "Gate Entry",
    "parentfield": "cards",
    "parenttype": "Dashboard"
   },
   {
    "card": "Sell Delivery",
    "parent": "Gate Entry",
    "parentfield": "cards",
    "parenttype": "Dashboard"
   },
   {
    "card": "Visitor On Visit Today",
    "parent": "Gate Entry",
    "parentfield": "cards",
    "parenttype": "Dashboard"
   },
   {
    "card": "Employee Go Out But Not Returned",
    "parent": "Gate Entry",
    "parentfield": "cards",
    "parenttype": "Dashboard"
   }
  ],
  "chart_options": null,
  "charts": [
   {
    "chart": "Completed Gate Entry",
    "parent": "Gate Entry",
    "parentfield": "charts",
    "parenttype": "Dashboard",
    "width": "Half"
   }
  ],
  "dashboard_name": "Gate Entry",
  "docstatus": 0,
  "doctype": "Dashboard",
  "is_default": 0,
  "is_standard": 0,
  "modified": "2023-10-17 16:33:21.244374",
  "module": "Advantisquartz",
  "name": "Gate Entry"
 }
]